{
  "parent": "minecraft:recipes/root",
  "criteria": {
    "has_raw_peacock": {
      "conditions": {
        "items": [
          {
            "items": "ow:raw_peacock"
          }
        ]
      },
      "trigger": "minecraft:inventory_changed"
    },
    "has_the_recipe": {
      "conditions": {
        "recipe": "ow:cooked_peacock_from_smoking"
      },
      "trigger": "minecraft:recipe_unlocked"
    }
  },
  "requirements": [
    [
      "has_the_recipe",
      "has_raw_peacock"
    ]
  ],
  "rewards": {
    "recipes": [
      "ow:cooked_peacock_from_smoking"
    ]
  }
}